tensorflow_federated/__init__.py
tensorflow_federated/version.py
tensorflow_federated/data/worker_binary
tensorflow_federated/proto/__init__.py
tensorflow_federated/proto/v0/__init__.py
tensorflow_federated/proto/v0/array_pb2.py
tensorflow_federated/proto/v0/computation_pb2.py
tensorflow_federated/proto/v0/data_type_pb2.py
tensorflow_federated/proto/v0/executor_pb2.py
tensorflow_federated/proto/v0/executor_pb2_grpc.py
tensorflow_federated/python/__init__.py
tensorflow_federated/python/aggregators/__init__.py
tensorflow_federated/python/aggregators/concat.py
tensorflow_federated/python/aggregators/differential_privacy.py
tensorflow_federated/python/aggregators/discretization.py
tensorflow_federated/python/aggregators/distributed_dp.py
tensorflow_federated/python/aggregators/encoded.py
tensorflow_federated/python/aggregators/factory.py
tensorflow_federated/python/aggregators/factory_utils.py
tensorflow_federated/python/aggregators/hadamard.py
tensorflow_federated/python/aggregators/mean.py
tensorflow_federated/python/aggregators/measurements.py
tensorflow_federated/python/aggregators/modular_clipping.py
tensorflow_federated/python/aggregators/primitives.py
tensorflow_federated/python/aggregators/quantile_estimation.py
tensorflow_federated/python/aggregators/robust.py
tensorflow_federated/python/aggregators/rotation.py
tensorflow_federated/python/aggregators/sampling.py
tensorflow_federated/python/aggregators/secure.py
tensorflow_federated/python/aggregators/sum_factory.py
tensorflow_federated/python/analytics/__init__.py
tensorflow_federated/python/analytics/count_distinct.py
tensorflow_federated/python/analytics/data_processing.py
tensorflow_federated/python/analytics/differential_privacy.py
tensorflow_federated/python/analytics/histogram_processing.py
tensorflow_federated/python/analytics/heavy_hitters/__init__.py
tensorflow_federated/python/analytics/heavy_hitters/iblt/__init__.py
tensorflow_federated/python/analytics/heavy_hitters/iblt/chunkers.py
tensorflow_federated-0.87.0.dist-info/LICENSE
tensorflow_federated-0.87.0.dist-info/METADATA
tensorflow_federated-0.87.0.dist-info/WHEEL
tensorflow_federated-0.87.0.dist-info/top_level.txt
tensorflow_federated-0.87.0.dist-info/RECORD
